hanilab/__init__.py
hanilab/app.py
hanilab/object_detection.py
hanilab-0.1.0.dist-info/LICENSE
hanilab-0.1.0.dist-info/METADATA
hanilab-0.1.0.dist-info/WHEEL
hanilab-0.1.0.dist-info/entry_points.txt
hanilab-0.1.0.dist-info/top_level.txt
hanilab-0.1.0.dist-info/RECORD
