Metadata-Version: 2.1
Name: hanilab
Version: 0.1.0
License-File: LICENSE
Requires-Dist: opencv-python-headless
Requires-Dist: torch
Requires-Dist: torchvision
Requires-Dist: matplotlib
Requires-Dist: flask
